pytally
