Metadata-Version: 1.2
Name: pytally
Version: 0.5
Summary: Simple bookkeeping
Home-page: https://github.com/mlackman/pytally
Author: Mika Lackman
Author-email: mika.lackman@gmail.com
License: MIT
Platform: UNKNOWN
Requires-Python: >3.6
